dataladmetadatamodel/__init__.py
dataladmetadatamodel/_version.py
dataladmetadatamodel/common.py
dataladmetadatamodel/datasettree.py
dataladmetadatamodel/filetree.py
dataladmetadatamodel/log.py
dataladmetadatamodel/mappableobject.py
dataladmetadatamodel/metadata.py
dataladmetadatamodel/metadatapath.py
dataladmetadatamodel/metadatarootrecord.py
dataladmetadatamodel/metadatasource.py
dataladmetadatamodel/modifiableobject.py
dataladmetadatamodel/mtreenode.py
dataladmetadatamodel/mtreeproxy.py
dataladmetadatamodel/text.py
dataladmetadatamodel/uuidset.py
dataladmetadatamodel/versionlist.py
dataladmetadatamodel/mapper/__init__.py
dataladmetadatamodel/mapper/mapper.py
dataladmetadatamodel/mapper/reference.py
dataladmetadatamodel/mapper/gitmapper/__init__.py
dataladmetadatamodel/mapper/gitmapper/gitblobcache.py
dataladmetadatamodel/mapper/gitmapper/localcache.py
dataladmetadatamodel/mapper/gitmapper/metadatamapper.py
dataladmetadatamodel/mapper/gitmapper/metadatarootrecordmapper.py
dataladmetadatamodel/mapper/gitmapper/mtreenodemapper.py
dataladmetadatamodel/mapper/gitmapper/objectreference.py
dataladmetadatamodel/mapper/gitmapper/textmapper.py
dataladmetadatamodel/mapper/gitmapper/treeupdater.py
dataladmetadatamodel/mapper/gitmapper/utils.py
dataladmetadatamodel/mapper/gitmapper/uuidsetmapper.py
dataladmetadatamodel/mapper/gitmapper/versionlistmapper.py
dataladmetadatamodel/mapper/gitmapper/gitbackend/__init__.py
dataladmetadatamodel/mapper/gitmapper/gitbackend/subprocess.py
dataladmetadatamodel/mapper/gitmapper/tests/__init__.py
dataladmetadatamodel/mapper/gitmapper/tests/test_localcache.py
dataladmetadatamodel/mapper/gitmapper/tests/test_metadatamapper.py
dataladmetadatamodel/mapper/gitmapper/tests/test_metadatarootrecordmapper.py
dataladmetadatamodel/mapper/gitmapper/tests/test_mtreenodemapper.py
dataladmetadatamodel/mapper/gitmapper/tests/test_objectreferences.py
dataladmetadatamodel/mapper/gitmapper/tests/test_treeupdater.py
datalad_metadata_model-0.3.11.dist-info/LICENSE
datalad_metadata_model-0.3.11.dist-info/METADATA
datalad_metadata_model-0.3.11.dist-info/WHEEL
datalad_metadata_model-0.3.11.dist-info/entry_points.txt
datalad_metadata_model-0.3.11.dist-info/top_level.txt
datalad_metadata_model-0.3.11.dist-info/RECORD
