Metadata-Version: 2.1
Name: datalad-metadata-model
Version: 0.3.11
Summary: Datalad Metadata Model
Home-page: https://github.com/christian-monch/metadata-model
Author: The Datalad Team
Author-email: christian.moench@web.de
License: MIT
Classifier: Development Status :: 4 - Beta
Classifier: Programming Language :: Python :: 3
Classifier: License :: OSI Approved :: MIT License
Classifier: Operating System :: OS Independent
Requires-Python: >=3.7
License-File: LICENSE
Requires-Dist: appdirs
Requires-Dist: click
Requires-Dist: fasteners
